smindex/__init__.py
smindex/_globals.py
smindex/convert_index_data.py
smindex/convert_substorm_data.py
smindex/database.py
smindex/download_indices.py
smindex/download_substorms.py
smindex/indices.py
smindex/substorms.py
smindex/update_config.py
smindex/api/__init__.py
smindex/api/check_username.py
smindex/api/get_url.py
smindex/api/request_indices.py
smindex/api/request_substorms.py
smindex-2.0.0.dist-info/licenses/LICENSE
smindex-2.0.0.dist-info/METADATA
smindex-2.0.0.dist-info/WHEEL
smindex-2.0.0.dist-info/top_level.txt
smindex-2.0.0.dist-info/RECORD
