Metadata-Version: 2.4
Name: smindex
Version: 2.0.0
Summary: A tiny module for reading SuperMAG indices and substorm lists.
Home-page: https://github.com/mattkjames7/smindex
Author: Matthew Knight James
Author-email: mattkjames7@gmail.com
Classifier: Programming Language :: Python :: 3
Classifier: License :: OSI Approved :: MIT License
Classifier: Operating System :: POSIX
License-File: LICENSE
Requires-Dist: numpy
Requires-Dist: DateTimeTools
Requires-Dist: requests
Requires-Dist: tqdm
Dynamic: author
Dynamic: author-email
Dynamic: classifier
Dynamic: description
Dynamic: description-content-type
Dynamic: home-page
Dynamic: license-file
Dynamic: requires-dist
Dynamic: summary
